payman_sdk/__init__.py
payman_sdk/client.py
payman_sdk/types.py
payman_sdk/utils.py
paymanai_sdk-1.0.8.dist-info/LICENSE
paymanai_sdk-1.0.8.dist-info/METADATA
paymanai_sdk-1.0.8.dist-info/WHEEL
paymanai_sdk-1.0.8.dist-info/RECORD
