Metadata-Version: 2.1
Name: paymanai-sdk
Version: 1.0.8
Summary: Python SDK for the Payman AI Platform
Home-page: https://github.com/payman-ai/payman-sdk-python
License: MIT
Author: Payman AI
Author-email: engineering@payman.ai
Requires-Python: >=3.9,<4.0
Classifier: Development Status :: 4 - Beta
Classifier: Intended Audience :: Developers
Classifier: License :: OSI Approved :: MIT License
Classifier: Programming Language :: Python :: 3
Classifier: Programming Language :: Python :: 3.9
Classifier: Programming Language :: Python :: 3.10
Classifier: Programming Language :: Python :: 3.11
Classifier: Programming Language :: Python :: 3.12
Classifier: Programming Language :: Python :: 3.13
Requires-Dist: requests (>=2.31.0,<3.0.0)
Project-URL: Repository, https://github.com/payman-ai/payman-sdk-python
